<ti:work xmlns:ti="http://chs.harvard.edu/xmlns/cts" urn="urn:cts:frenchLit:pos2002.pos200211" xml:lang="fr" groupUrn="urn:cts:frenchLit:pos2002">
  <ti:title xml:lang="fr">La traduction castillane du </ti:title>

  <ti:edition urn="urn:cts:frenchLit:pos2002.pos200211.positionThese-fr1" workUrn="urn:cts:frenchLit:pos2002.pos200211">
    <ti:label xml:lang="fr">La traduction castillane du </ti:label>
    <ti:description xml:lang="fr">Édition et commentaire (Bibl. nat. de Fr., esp. 458).</ti:description>
  </ti:edition>

</ti:work>
