<ti:work xmlns:ti="http://chs.harvard.edu/xmlns/cts" urn="urn:cts:frenchLit:pos2011.pos201116" xml:lang="fr" groupUrn="urn:cts:frenchLit:pos2011">
  <ti:title xml:lang="fr">Léon Bloy et le Moyen Âge l’imaginaire catholique renouvelé ?</ti:title>

  <ti:edition urn="urn:cts:frenchLit:pos2011.pos201116.positionThese-fr1" workUrn="urn:cts:frenchLit:pos2011.pos201116">
    <ti:label xml:lang="fr">Léon Bloy et le Moyen Âge l’imaginaire catholique renouvelé ?</ti:label>
    <ti:description xml:lang="fr"></ti:description>
  </ti:edition>

</ti:work>
