<ti:work xmlns:ti="http://chs.harvard.edu/xmlns/cts" urn="urn:cts:frenchLit:pos2000.pos200006" xml:lang="fr" groupUrn="urn:cts:frenchLit:pos2000">
  <ti:title xml:lang="fr">Éditions et adaptations de l’&lt;hi xmlns="http://www.tei-c.org/ns/1.0" rend="i"&gt;Histoire de Mélusine&lt;/hi&gt; de Jean d’Arras (&lt;num xmlns="http://www.tei-c.org/ns/1.0"&gt;xv&lt;hi rend="sup"&gt;e&lt;/hi&gt;&lt;/num&gt;-&lt;num xmlns="http://www.tei-c.org/ns/1.0"&gt;xix&lt;hi rend="sup"&gt;e&lt;/hi&gt;&lt;/num&gt; siècle)</ti:title>

  <ti:edition urn="urn:cts:frenchLit:pos2000.pos200006.positionThese-fr1" workUrn="urn:cts:frenchLit:pos2000.pos200006">
    <ti:label xml:lang="fr">Éditions et adaptations de l’&lt;hi xmlns="http://www.tei-c.org/ns/1.0" rend="i"&gt;Histoire de Mélusine&lt;/hi&gt; de Jean d’Arras (&lt;num xmlns="http://www.tei-c.org/ns/1.0"&gt;xv&lt;hi rend="sup"&gt;e&lt;/hi&gt;&lt;/num&gt;-&lt;num xmlns="http://www.tei-c.org/ns/1.0"&gt;xix&lt;hi rend="sup"&gt;e&lt;/hi&gt;&lt;/num&gt; siècle)</ti:label>
    <ti:description xml:lang="fr">Les aventures d’un roman médiéval.</ti:description>
  </ti:edition>

</ti:work>
