<ti:work xmlns:ti="http://chs.harvard.edu/xmlns/cts" urn="urn:cts:frenchLit:pos2005.pos200527" xml:lang="fr" groupUrn="urn:cts:frenchLit:pos2005">

  <ti:title xml:lang="fr">Missionnaires et chrétientés en Chine dans la deuxième moitié du xviiie siècle.</ti:title><ti:edition urn="urn:cts:frenchLit:pos2005.pos200527.positionThese-fr1" workUrn="urn:cts:frenchLit:pos2005.pos200527">
  <ti:label xml:lang="fr">Missionnaires et chrétientés en Chine dans la deuxième moitié du xviiie siècle.</ti:label><ti:description xml:lang="fr">L’exemple de la mission du Sichuan (1746-1769)</ti:description></ti:edition>

</ti:work>
