<ti:work xmlns:cpt="http://purl.org/capitains/ns/1.0#" xmlns:dc="http://purl.org/dc/elements/1.1/" xmlns:dct="http://purl.org/dc/terms/" xmlns:ti="http://chs.harvard.edu/xmlns/cts" xmlns:rdf="http://www.w3.org/1999/02/22-rdf-syntax-ns#" urn="urn:cts:frenchLit:pos2012.pos201208" xml:lang="fr" groupUrn="urn:cts:frenchLit:pos2012">

  <ti:title xml:lang="fr">Paris capitale de guerre (1792-1794)</ti:title><ti:edition urn="urn:cts:frenchLit:pos2012.pos201208.positionThese-fr1" workUrn="urn:cts:frenchLit:pos2012.pos201208">
  <ti:label xml:lang="fr">Paris capitale de guerre (1792-1794)</ti:label></ti:edition>
  
  <cpt:structured-metadata>
    <dc:publisher xml:lang="fr">École nationale des chartes</dc:publisher>
    <dc:date rdf:datatype="xsd:gYear">2012</dc:date>
    <dct:relation xml:lang="fr">http://www.sudoc.fr/159123623</dct:relation>
    <dc:creator xml:lang="fr">Diallo, Malik</dc:creator>
  </cpt:structured-metadata>

</ti:work>
